pingpongx/__init__.py
pingpongx/main.py
pingpongx/models.py
pingpongx/utils.py
pingpongx/routes/__init__.py
pingpongx/routes/auth_routes.py
pingpongx/routes/notification.py
pingpongx/routes/user_preferences.py
pingpongx/services/__init__.py
pingpongx/services/auth_middleware.py
pingpongx/services/auth_service.py
pingpongx/services/email_service.py
pingpongx/services/firestore_service.py
pingpongx/services/kafka_consumer.py
pingpongx/services/kafka_producer.py
pingpongx/services/notification.py
pingpongx/services/push_service.py
pingpongx/services/redis_service.py
pingpongx/services/sms_service.py
pingpongx/services/user_preferences.py
pingpongx-0.1.8.dist-info/METADATA
pingpongx-0.1.8.dist-info/WHEEL
pingpongx-0.1.8.dist-info/top_level.txt
pingpongx-0.1.8.dist-info/RECORD
