Metadata-Version: 2.1
Name: pingpongx
Version: 0.1.8
Summary: A dynamic notification delivery system with Redis and Kafka integration.
Home-page: https://github.com/karan-kap00r/PingPong
Author: Karan Kapoor
Author-email: kaykay9464769@gmail.com
Classifier: Programming Language :: Python :: 3
Classifier: License :: OSI Approved :: MIT License
Classifier: Operating System :: OS Independent
Requires-Python: >=3.8
Requires-Dist: fastapi
Requires-Dist: uvicorn
Requires-Dist: redis
Requires-Dist: kafka-python
Requires-Dist: google-cloud-firestore
Requires-Dist: requests
Requires-Dist: pydantic
Requires-Dist: Jinja2
Requires-Dist: PyJWT
Requires-Dist: passlib
Requires-Dist: bcrypt
Requires-Dist: twilio
Requires-Dist: google-cloud-secret-manager ==2.22.0
